datasketchesframework/__init__.py
datasketchesframework/python_wrapper.py
lib/CMakeLists.txt
lib/CMakePresets.json
lib/__init__.py
lib/conanfile.txt
lib/include/data-sketches.hpp
lib/scripts/build.sh
lib/scripts/configure.sh
lib/scripts/test.sh
lib/src/data-sketches.cpp
lib/test/CMakeLists.txt
lib/test/data-sketches-tests.cpp
lib/test/data-sketches-tests.hpp
lib/test/main.cpp
lib/test/python-usage.py
datasketchesframework-0.0.4.dist-info/METADATA
datasketchesframework-0.0.4.dist-info/WHEEL
datasketchesframework-0.0.4.dist-info/top_level.txt
datasketchesframework-0.0.4.dist-info/RECORD
