Metadata-Version: 2.1
Name: datasketchesframework
Version: 0.0.4
Summary: Library for operating on data sketches
Home-page: UNKNOWN
Author: Karol Janic
Author-email: <29999@student.pwr.edu.pl>
License: UNKNOWN
Keywords: python,data sketches,data stream,data analysis
Platform: UNKNOWN
Requires-Dist: numpy
